{
  "schemaVersion": "temporal-history-fixture/v1",
  "fixture": "timer-race",
  "history": "timeout",
  "generatedBy": "scripts/fixtures/generate-histories.ts",
  "generationCommand": "bun run fixtures:generate-histories",
  "temporalSdkVersion": "^1.18.1",
  "testEnvironment": "TestWorkflowEnvironment.createTimeSkipping",
  "workflowType": "timerRaceWorkflow",
  "workflowId": "timer-race-timeout",
  "runIdNormalization": { "replacement": "timeout-run-id" },
  "identityNormalization": {
    "replacement": "temporal-explorer-fixture-worker"
  },
  "timestampNormalization": "eventTime values are set to 2026-01-01T00:00:00.000Z plus eventId milliseconds.",
  "binaryChecksumNormalization": "workflowTaskCompletedEventAttributes.binaryChecksum hash suffixes are replaced with fixture-binary-checksum.",
  "eventCount": 16,
  "eventTypes": {
    "1": 1,
    "2": 1,
    "5": 3,
    "6": 3,
    "7": 3,
    "10": 1,
    "11": 1,
    "12": 1,
    "17": 1,
    "18": 1
  },
  "contentSha256": "538c740be815c6d3c15affda4261fd2c8b280bbbaf9fa40a250339c9e181ed26"
}
